<annotation>
	<folder>train</folder>
	<filename>DJI_20191231173735_0002_frame_4200.png</filename>
	<path>C:\Users\realt\AI\DroneTruth\train\DJI_20191231173735_0002_frame_4200.png</path>
	<source>
		<database>Unknown</database>
	</source>
	<size>
		<width>3840</width>
		<height>2160</height>
		<depth>3</depth>
	</size>
	<segmented>0</segmented>
	<object>
		<name>free-zone</name>
		<pose>Unspecified</pose>
		<truncated>0</truncated>
		<difficult>0</difficult>
		<bndbox>
			<xmin>133</xmin>
			<ymin>12</ymin>
			<xmax>1549</xmax>
			<ymax>1592</ymax>
		</bndbox>
		<extra/>
	</object>
	<object>
		<name>free-zone</name>
		<pose>Unspecified</pose>
		<truncated>1</truncated>
		<difficult>0</difficult>
		<bndbox>
			<xmin>1</xmin>
			<ymin>1622</ymin>
			<xmax>1084</xmax>
			<ymax>2141</ymax>
		</bndbox>
		<extra/>
	</object>
	<object>
		<name>small-vehicle</name>
		<pose>Unspecified</pose>
		<truncated>0</truncated>
		<difficult>0</difficult>
		<robndbox>
			<cx>2541.0</cx>
			<cy>800.0</cy>
			<w>71.0</w>
			<h>196.0001</h>
			<angle>5.445427</angle>
		</robndbox>
		<extra/>
	</object>
	<object>
		<name>small-vehicle</name>
		<pose>Unspecified</pose>
		<truncated>0</truncated>
		<difficult>0</difficult>
		<robndbox>
			<cx>2698.0</cx>
			<cy>972.0</cy>
			<w>66.0</w>
			<h>167.0001</h>
			<angle>5.508282</angle>
		</robndbox>
		<extra/>
	</object>
	<object>
		<name>small-vehicle</name>
		<pose>Unspecified</pose>
		<truncated>0</truncated>
		<difficult>0</difficult>
		<robndbox>
			<cx>2837.0</cx>
			<cy>1115.0</cy>
			<w>68.0</w>
			<h>202.9999</h>
			<angle>5.438633</angle>
		</robndbox>
		<extra/>
	</object>
	<object>
		<name>small-vehicle</name>
		<pose>Unspecified</pose>
		<truncated>0</truncated>
		<difficult>0</difficult>
		<robndbox>
			<cx>2982.0</cx>
			<cy>1250.0</cy>
			<w>71.0001</w>
			<h>183.0001</h>
			<angle>5.510475</angle>
		</robndbox>
		<extra/>
	</object>
	<object>
		<name>small-vehicle</name>
		<pose>Unspecified</pose>
		<truncated>0</truncated>
		<difficult>0</difficult>
		<robndbox>
			<cx>2673.0</cx>
			<cy>1946.0</cy>
			<w>67.9999</w>
			<h>160.9999</h>
			<angle>1.783629</angle>
		</robndbox>
		<extra/>
	</object>
	<object>
		<name>small-vehicle</name>
		<pose>Unspecified</pose>
		<truncated>0</truncated>
		<difficult>0</difficult>
		<robndbox>
			<cx>1184.0</cx>
			<cy>1681.0</cy>
			<w>62.0</w>
			<h>154.9999</h>
			<angle>1.258908</angle>
		</robndbox>
		<extra/>
	</object>
	<object>
		<name>small-vehicle</name>
		<pose>Unspecified</pose>
		<truncated>0</truncated>
		<difficult>0</difficult>
		<robndbox>
			<cx>2181.0</cx>
			<cy>1634.0</cy>
			<w>70.0</w>
			<h>172.0</h>
			<angle>1.572435</angle>
		</robndbox>
		<extra/>
	</object>
	<object>
		<name>small-vehicle</name>
		<pose>Unspecified</pose>
		<truncated>0</truncated>
		<difficult>0</difficult>
		<robndbox>
			<cx>2761.0</cx>
			<cy>1646.0</cy>
			<w>66.9999</w>
			<h>167.9999</h>
			<angle>1.643911</angle>
		</robndbox>
		<extra/>
	</object>
	<object>
		<name>small-vehicle</name>
		<pose>Unspecified</pose>
		<truncated>0</truncated>
		<difficult>0</difficult>
		<robndbox>
			<cx>3346.0</cx>
			<cy>1570.0</cy>
			<w>68.0001</w>
			<h>161.9999</h>
			<angle>4.797863</angle>
		</robndbox>
		<extra/>
	</object>
	<object>
		<name>small-vehicle</name>
		<pose>Unspecified</pose>
		<truncated>0</truncated>
		<difficult>0</difficult>
		<robndbox>
			<cx>2522.0</cx>
			<cy>1189.0</cy>
			<w>65.0</w>
			<h>157.0</h>
			<angle>5.420384</angle>
		</robndbox>
		<extra/>
	</object>
	<object>
		<name>small-vehicle</name>
		<pose>Unspecified</pose>
		<truncated>0</truncated>
		<difficult>0</difficult>
		<robndbox>
			<cx>1756.0</cx>
			<cy>1571.0</cy>
			<w>64.0</w>
			<h>157.0002</h>
			<angle>2.251475</angle>
		</robndbox>
		<extra/>
	</object>
	<object>
		<name>small-vehicle</name>
		<pose>Unspecified</pose>
		<truncated>0</truncated>
		<difficult>0</difficult>
		<robndbox>
			<cx>1626.0</cx>
			<cy>1140.0</cy>
			<w>67.0</w>
			<h>146.0</h>
			<angle>3.263766</angle>
		</robndbox>
		<extra/>
	</object>
	<object>
		<name>small-vehicle</name>
		<pose>Unspecified</pose>
		<truncated>0</truncated>
		<difficult>0</difficult>
		<robndbox>
			<cx>2266.0</cx>
			<cy>913.0</cy>
			<w>69.0001</w>
			<h>175.0</h>
			<angle>5.637255</angle>
		</robndbox>
		<extra/>
	</object>
	<object>
		<name>small-vehicle</name>
		<pose>Unspecified</pose>
		<truncated>0</truncated>
		<difficult>0</difficult>
		<robndbox>
			<cx>1728.0</cx>
			<cy>700.0</cy>
			<w>67.0</w>
			<h>162.0</h>
			<angle>3.373089</angle>
		</robndbox>
		<extra/>
	</object>
	<object>
		<name>small-vehicle</name>
		<pose>Unspecified</pose>
		<truncated>0</truncated>
		<difficult>0</difficult>
		<robndbox>
			<cx>1790.0</cx>
			<cy>274.0</cy>
			<w>74.0</w>
			<h>179.0</h>
			<angle>3.234088</angle>
		</robndbox>
		<extra/>
	</object>
	<object>
		<name>large-vehicle</name>
		<pose>Unspecified</pose>
		<truncated>0</truncated>
		<difficult>0</difficult>
		<robndbox>
			<cx>2335.0</cx>
			<cy>746.0</cy>
			<w>78.0002</w>
			<h>292.0002</h>
			<angle>5.779222</angle>
		</robndbox>
		<extra/>
	</object>
</annotation>
