<annotation>
	<folder>train</folder>
	<filename>DJI_20191231173735_0003_frame_7600.png</filename>
	<path>C:\Users\realt\AI\DroneTruth\train\DJI_20191231173735_0003_frame_7600.png</path>
	<source>
		<database>Unknown</database>
	</source>
	<size>
		<width>3840</width>
		<height>2160</height>
		<depth>3</depth>
	</size>
	<segmented>0</segmented>
	<object>
		<name>small-vehicle</name>
		<pose>Unspecified</pose>
		<truncated>0</truncated>
		<difficult>0</difficult>
		<robndbox>
			<cx>2690.0</cx>
			<cy>1954.0</cy>
			<w>71.0</w>
			<h>162.0001</h>
			<angle>1.800752</angle>
		</robndbox>
		<extra/>
	</object>
	<object>
		<name>small-vehicle</name>
		<pose>Unspecified</pose>
		<truncated>0</truncated>
		<difficult>0</difficult>
		<robndbox>
			<cx>3136.0</cx>
			<cy>1519.0</cy>
			<w>71.9999</w>
			<h>177.0002</h>
			<angle>5.001418</angle>
		</robndbox>
		<extra/>
	</object>
	<object>
		<name>small-vehicle</name>
		<pose>Unspecified</pose>
		<truncated>0</truncated>
		<difficult>0</difficult>
		<robndbox>
			<cx>3002.0</cx>
			<cy>1257.0</cy>
			<w>77.0</w>
			<h>186.0003</h>
			<angle>5.509142</angle>
		</robndbox>
		<extra/>
	</object>
	<object>
		<name>small-vehicle</name>
		<pose>Unspecified</pose>
		<truncated>0</truncated>
		<difficult>0</difficult>
		<robndbox>
			<cx>2857.0</cx>
			<cy>1124.0</cy>
			<w>79.0</w>
			<h>205.0</h>
			<angle>5.427974</angle>
		</robndbox>
		<extra/>
	</object>
	<object>
		<name>small-vehicle</name>
		<pose>Unspecified</pose>
		<truncated>0</truncated>
		<difficult>0</difficult>
		<robndbox>
			<cx>2720.0</cx>
			<cy>980.0</cy>
			<w>70.9999</w>
			<h>168.0001</h>
			<angle>5.517511</angle>
		</robndbox>
		<extra/>
	</object>
	<object>
		<name>small-vehicle</name>
		<pose>Unspecified</pose>
		<truncated>0</truncated>
		<difficult>0</difficult>
		<robndbox>
			<cx>2561.0</cx>
			<cy>810.0</cy>
			<w>78.9999</w>
			<h>197.0001</h>
			<angle>5.4505</angle>
		</robndbox>
		<extra/>
	</object>
	<object>
		<name>small-vehicle</name>
		<pose>Unspecified</pose>
		<truncated>0</truncated>
		<difficult>0</difficult>
		<robndbox>
			<cx>394.0</cx>
			<cy>1801.0</cy>
			<w>70.0</w>
			<h>174.0</h>
			<angle>4.465354</angle>
		</robndbox>
		<extra/>
	</object>
	<object>
		<name>two-wheeler</name>
		<pose>Unspecified</pose>
		<truncated>0</truncated>
		<difficult>0</difficult>
		<robndbox>
			<cx>2903.0</cx>
			<cy>1395.0</cy>
			<w>28.0</w>
			<h>67.0</h>
			<angle>5.19881</angle>
		</robndbox>
		<extra/>
	</object>
</annotation>
