   <annotation>
	<folder>train</folder>
	<filename>DJI_20220405122203_0006_frame_9000.png</filename>
	<path>C:\Users\realt\AI\DroneTruth\train\DJI_20220405122203_0006_frame_9000.png</path>
	<source>
		<database>DroneTruth</database>
	</source>
	<size>
		<width>3840</width>
		<height>2160</height>
		<depth>3</depth>
	</size>
	<segmented>0</segmented>
       <object>
		<name>small-vehicle</name>
		<pose>Unspecified</pose>
		<truncated>0</truncated>
		<difficult>0</difficult>
		<robndbox>
			<cx>806.0</cx>
			<cy>1554.0</cy>
			<w>81.00003814697266</w>
			<h>176.00001525878906</h>
			<angle>3.09604014478702</angle>
		</robndbox>
		<extra/>
	</object>
   <object>
		<name>small-vehicle</name>
		<pose>Unspecified</pose>
		<truncated>0</truncated>
		<difficult>0</difficult>
		<robndbox>
			<cx>2579.0</cx>
			<cy>498.0</cy>
			<w>82.99996948242188</w>
			<h>199.00003051757812</h>
			<angle>-0.3369128110482559</angle>
		</robndbox>
		<extra/>
	</object>
   <object>
		<name>small-vehicle</name>
		<pose>Unspecified</pose>
		<truncated>0</truncated>
		<difficult>0</difficult>
		<robndbox>
			<cx>2741.0</cx>
			<cy>936.0</cy>
			<w>81.00000762939453</w>
			<h>192.00006103515625</h>
			<angle>-0.35968613898313195</angle>
		</robndbox>
		<extra/>
	</object>
   <object>
		<name>small-vehicle</name>
		<pose>Unspecified</pose>
		<truncated>0</truncated>
		<difficult>0</difficult>
		<robndbox>
			<cx>2858.0</cx>
			<cy>887.0</cy>
			<w>81.00001525878906</w>
			<h>187.00006103515625</h>
			<angle>-0.34968462160234315</angle>
		</robndbox>
		<extra/>
	</object>
   <object>
		<name>small-vehicle</name>
		<pose>Unspecified</pose>
		<truncated>0</truncated>
		<difficult>0</difficult>
		<robndbox>
			<cx>3196.0</cx>
			<cy>1499.0</cy>
			<w>82.99981689453125</w>
			<h>195.99996948242188</h>
			<angle>-0.3524851889834983</angle>
		</robndbox>
		<extra/>
	</object>
   <object>
		<name>small-vehicle</name>
		<pose>Unspecified</pose>
		<truncated>0</truncated>
		<difficult>0</difficult>
		<robndbox>
			<cx>2304.0</cx>
			<cy>1317.0</cy>
			<w>75.00001525878906</w>
			<h>188.00022888183594</h>
			<angle>-1.5120408874058437</angle>
		</robndbox>
		<extra/>
	</object>
   <object>
		<name>small-vehicle</name>
		<pose>Unspecified</pose>
		<truncated>0</truncated>
		<difficult>0</difficult>
		<robndbox>
			<cx>2565.0</cx>
			<cy>1366.0</cy>
			<w>73.9999008178711</w>
			<h>187.0001220703125</h>
			<angle>-1.179312621857692</angle>
		</robndbox>
		<extra/>
	</object>
  </annotation>
