   <annotation>
	<folder>train</folder>
	<filename>DJI_20220405123814_0007_frame_5400.png</filename>
	<path>C:\Users\realt\AI\DroneTruth\train\DJI_20220405123814_0007_frame_5400.png</path>
	<source>
		<database>DroneTruth</database>
	</source>
	<size>
		<width>3840</width>
		<height>2160</height>
		<depth>3</depth>
	</size>
	<segmented>0</segmented>
       <object>
		<name>small-vehicle</name>
		<pose>Unspecified</pose>
		<truncated>0</truncated>
		<difficult>0</difficult>
		<robndbox>
			<cx>135.0</cx>
			<cy>1014.0</cy>
			<w>65.00000762939453</w>
			<h>147.0</h>
			<angle>-0.5908462833229547</angle>
		</robndbox>
		<extra/>
	</object>
   <object>
		<name>small-vehicle</name>
		<pose>Unspecified</pose>
		<truncated>0</truncated>
		<difficult>0</difficult>
		<robndbox>
			<cx>213.0</cx>
			<cy>986.0</cy>
			<w>63.00001525878906</w>
			<h>125.00003051757812</h>
			<angle>-0.4977457280151606</angle>
		</robndbox>
		<extra/>
	</object>
   <object>
		<name>small-vehicle</name>
		<pose>Unspecified</pose>
		<truncated>0</truncated>
		<difficult>0</difficult>
		<robndbox>
			<cx>395.0</cx>
			<cy>991.0</cy>
			<w>64.9999885559082</w>
			<h>146.0</h>
			<angle>-0.8341396884130018</angle>
		</robndbox>
		<extra/>
	</object>
   <object>
		<name>small-vehicle</name>
		<pose>Unspecified</pose>
		<truncated>0</truncated>
		<difficult>0</difficult>
		<robndbox>
			<cx>517.0</cx>
			<cy>992.0</cy>
			<w>60.99995422363281</w>
			<h>118.0000228881836</h>
			<angle>-0.5302158038140016</angle>
		</robndbox>
		<extra/>
	</object>
   <object>
		<name>small-vehicle</name>
		<pose>Unspecified</pose>
		<truncated>0</truncated>
		<difficult>0</difficult>
		<robndbox>
			<cx>562.0</cx>
			<cy>665.0</cy>
			<w>62.99995422363281</w>
			<h>142.00001525878906</h>
			<angle>-0.9258808468919048</angle>
		</robndbox>
		<extra/>
	</object>
   <object>
		<name>small-vehicle</name>
		<pose>Unspecified</pose>
		<truncated>0</truncated>
		<difficult>0</difficult>
		<robndbox>
			<cx>562.0</cx>
			<cy>559.0</cy>
			<w>62.00001525878906</w>
			<h>142.00003051757812</h>
			<angle>-0.9964915714435324</angle>
		</robndbox>
		<extra/>
	</object>
   <object>
		<name>small-vehicle</name>
		<pose>Unspecified</pose>
		<truncated>0</truncated>
		<difficult>0</difficult>
		<robndbox>
			<cx>566.0</cx>
			<cy>471.0</cy>
			<w>59.00001525878906</w>
			<h>137.0</h>
			<angle>-1.0203393796410145</angle>
		</robndbox>
		<extra/>
	</object>
   <object>
		<name>small-vehicle</name>
		<pose>Unspecified</pose>
		<truncated>0</truncated>
		<difficult>0</difficult>
		<robndbox>
			<cx>562.0</cx>
			<cy>378.0</cy>
			<w>55.0000114440918</w>
			<h>127.99998474121094</h>
			<angle>-1.0067803561991444</angle>
		</robndbox>
		<extra/>
	</object>
   <object>
		<name>small-vehicle</name>
		<pose>Unspecified</pose>
		<truncated>0</truncated>
		<difficult>0</difficult>
		<robndbox>
			<cx>553.0</cx>
			<cy>268.0</cy>
			<w>58.000003814697266</w>
			<h>130.00003051757812</h>
			<angle>-1.0020017722618528</angle>
		</robndbox>
		<extra/>
	</object>
   <object>
		<name>small-vehicle</name>
		<pose>Unspecified</pose>
		<truncated>0</truncated>
		<difficult>0</difficult>
		<robndbox>
			<cx>556.0</cx>
			<cy>177.0</cy>
			<w>58.0</w>
			<h>134.00003051757812</h>
			<angle>-1.0971155118407565</angle>
		</robndbox>
		<extra/>
	</object>
   <object>
		<name>small-vehicle</name>
		<pose>Unspecified</pose>
		<truncated>0</truncated>
		<difficult>0</difficult>
		<robndbox>
			<cx>559.0</cx>
			<cy>92.0</cy>
			<w>53.999996185302734</w>
			<h>124.00003051757812</h>
			<angle>-1.0798827062320744</angle>
		</robndbox>
		<extra/>
	</object>
   <object>
		<name>small-vehicle</name>
		<pose>Unspecified</pose>
		<truncated>0</truncated>
		<difficult>0</difficult>
		<robndbox>
			<cx>936.0</cx>
			<cy>1006.0</cy>
			<w>61.00001907348633</w>
			<h>142.00003051757812</h>
			<angle>-0.4636476090008061</angle>
		</robndbox>
		<extra/>
	</object>
   <object>
		<name>small-vehicle</name>
		<pose>Unspecified</pose>
		<truncated>0</truncated>
		<difficult>0</difficult>
		<robndbox>
			<cx>1109.0</cx>
			<cy>1011.0</cy>
			<w>62.000038146972656</w>
			<h>158.0000457763672</h>
			<angle>-0.5791768014120457</angle>
		</robndbox>
		<extra/>
	</object>
   <object>
		<name>small-vehicle</name>
		<pose>Unspecified</pose>
		<truncated>0</truncated>
		<difficult>0</difficult>
		<robndbox>
			<cx>1200.0</cx>
			<cy>1008.0</cy>
			<w>58.99993896484375</w>
			<h>140.00003051757812</h>
			<angle>-0.5441186581508205</angle>
		</robndbox>
		<extra/>
	</object>
   <object>
		<name>small-vehicle</name>
		<pose>Unspecified</pose>
		<truncated>0</truncated>
		<difficult>0</difficult>
		<robndbox>
			<cx>1394.0</cx>
			<cy>1017.0</cy>
			<w>59.00012969970703</w>
			<h>139.00001525878906</h>
			<angle>-0.4765711267261688</angle>
		</robndbox>
		<extra/>
	</object>
   <object>
		<name>small-vehicle</name>
		<pose>Unspecified</pose>
		<truncated>0</truncated>
		<difficult>0</difficult>
		<robndbox>
			<cx>1400.0</cx>
			<cy>1171.0</cy>
			<w>57.000003814697266</w>
			<h>138.99996948242188</h>
			<angle>-1.5671740131660865</angle>
		</robndbox>
		<extra/>
	</object>
   <object>
		<name>small-vehicle</name>
		<pose>Unspecified</pose>
		<truncated>0</truncated>
		<difficult>0</difficult>
		<robndbox>
			<cx>1489.0</cx>
			<cy>1018.0</cy>
			<w>61.999996185302734</w>
			<h>145.0000457763672</h>
			<angle>-0.49934665402548</angle>
		</robndbox>
		<extra/>
	</object>
   <object>
		<name>small-vehicle</name>
		<pose>Unspecified</pose>
		<truncated>0</truncated>
		<difficult>0</difficult>
		<robndbox>
			<cx>1579.0</cx>
			<cy>1012.0</cy>
			<w>58.999961853027344</w>
			<h>149.00006103515625</h>
			<angle>-0.5693128854304758</angle>
		</robndbox>
		<extra/>
	</object>
   <object>
		<name>small-vehicle</name>
		<pose>Unspecified</pose>
		<truncated>0</truncated>
		<difficult>0</difficult>
		<robndbox>
			<cx>1762.0</cx>
			<cy>1015.0</cy>
			<w>59.000038146972656</w>
			<h>148.00006103515625</h>
			<angle>-0.7997516042522124</angle>
		</robndbox>
		<extra/>
	</object>
   <object>
		<name>small-vehicle</name>
		<pose>Unspecified</pose>
		<truncated>0</truncated>
		<difficult>0</difficult>
		<robndbox>
			<cx>2555.0</cx>
			<cy>1146.0</cy>
			<w>59.00008773803711</w>
			<h>149.00015258789062</h>
			<angle>-1.6079414515019805</angle>
		</robndbox>
		<extra/>
	</object>
   <object>
		<name>small-vehicle</name>
		<pose>Unspecified</pose>
		<truncated>0</truncated>
		<difficult>0</difficult>
		<robndbox>
			<cx>2630.0</cx>
			<cy>1251.0</cy>
			<w>56.999942779541016</w>
			<h>149.00013732910156</h>
			<angle>-1.6010900617312238</angle>
		</robndbox>
		<extra/>
	</object>
   <object>
		<name>small-vehicle</name>
		<pose>Unspecified</pose>
		<truncated>0</truncated>
		<difficult>0</difficult>
		<robndbox>
			<cx>3173.0</cx>
			<cy>1242.0</cy>
			<w>60.000003814697266</w>
			<h>150.00006103515625</h>
			<angle>-1.5540186518405128</angle>
		</robndbox>
		<extra/>
	</object>
   <object>
		<name>small-vehicle</name>
		<pose>Unspecified</pose>
		<truncated>0</truncated>
		<difficult>0</difficult>
		<robndbox>
			<cx>3539.0</cx>
			<cy>1142.0</cy>
			<w>58.00003433227539</w>
			<h>134.0000762939453</h>
			<angle>-1.5670506856413513</angle>
		</robndbox>
		<extra/>
	</object>
   <object>
		<name>small-vehicle</name>
		<pose>Unspecified</pose>
		<truncated>0</truncated>
		<difficult>0</difficult>
		<robndbox>
			<cx>3573.0</cx>
			<cy>1250.0</cy>
			<w>59.00006866455078</w>
			<h>153.0001983642578</h>
			<angle>-1.574085804464898</angle>
		</robndbox>
		<extra/>
	</object>
   <object>
		<name>small-vehicle</name>
		<pose>Unspecified</pose>
		<truncated>0</truncated>
		<difficult>0</difficult>
		<robndbox>
			<cx>2792.0</cx>
			<cy>816.0</cy>
			<w>57.99995803833008</w>
			<h>151.0001220703125</h>
			<angle>-2.094074215140381</angle>
		</robndbox>
		<extra/>
	</object>
   <object>
		<name>small-vehicle</name>
		<pose>Unspecified</pose>
		<truncated>0</truncated>
		<difficult>0</difficult>
		<robndbox>
			<cx>2948.0</cx>
			<cy>728.0</cy>
			<w>58.999969482421875</w>
			<h>123.00007629394531</h>
			<angle>-2.0909529135248195</angle>
		</robndbox>
		<extra/>
	</object>
   <object>
		<name>small-vehicle</name>
		<pose>Unspecified</pose>
		<truncated>0</truncated>
		<difficult>0</difficult>
		<robndbox>
			<cx>3097.0</cx>
			<cy>644.0</cy>
			<w>58.00001525878906</w>
			<h>135.00010681152344</h>
			<angle>-1.999574093853318</angle>
		</robndbox>
		<extra/>
	</object>
   <object>
		<name>small-vehicle</name>
		<pose>Unspecified</pose>
		<truncated>0</truncated>
		<difficult>0</difficult>
		<robndbox>
			<cx>3238.0</cx>
			<cy>589.0</cy>
			<w>61.0</w>
			<h>157.99978637695312</h>
			<angle>-1.964855502040955</angle>
		</robndbox>
		<extra/>
	</object>
   <object>
		<name>small-vehicle</name>
		<pose>Unspecified</pose>
		<truncated>0</truncated>
		<difficult>0</difficult>
		<robndbox>
			<cx>3395.0</cx>
			<cy>531.0</cy>
			<w>62.99995040893555</w>
			<h>150.00018310546875</h>
			<angle>-1.9370090906723048</angle>
		</robndbox>
		<extra/>
	</object>
   <object>
		<name>small-vehicle</name>
		<pose>Unspecified</pose>
		<truncated>0</truncated>
		<difficult>0</difficult>
		<robndbox>
			<cx>3702.0</cx>
			<cy>442.0</cy>
			<w>64.00001907348633</w>
			<h>149.00003051757812</h>
			<angle>-1.6145394988861161</angle>
		</robndbox>
		<extra/>
	</object>
   <object>
		<name>large-vehicle</name>
		<pose>Unspecified</pose>
		<truncated>0</truncated>
		<difficult>0</difficult>
		<robndbox>
			<cx>3322.0</cx>
			<cy>378.0</cy>
			<w>86.99999237060547</w>
			<h>406.9998474121094</h>
			<angle>-1.8411504087413877</angle>
		</robndbox>
		<extra/>
	</object>
  </annotation>
