   <annotation>
	<folder>train</folder>
	<filename>DJI_20220405105332_0013_frame_0.png</filename>
	<path>C:\Users\realt\AI\DroneTruth\train\DJI_20220405105332_0013_frame_0.png</path>
	<source>
		<database>DroneTruth</database>
	</source>
	<size>
		<width>3840</width>
		<height>2160</height>
		<depth>3</depth>
	</size>
	<segmented>0</segmented>
       <object>
		<name>small-vehicle</name>
		<pose>Unspecified</pose>
		<truncated>0</truncated>
		<difficult>0</difficult>
		<robndbox>
			<cx>1658.0</cx>
			<cy>1475.0</cy>
			<w>57.99998474121094</w>
			<h>144.00010681152344</h>
			<angle>-1.5975311883589536</angle>
		</robndbox>
		<extra/>
	</object>
   <object>
		<name>small-vehicle</name>
		<pose>Unspecified</pose>
		<truncated>0</truncated>
		<difficult>0</difficult>
		<robndbox>
			<cx>2231.0</cx>
			<cy>1472.0</cy>
			<w>56.99992370605469</w>
			<h>144.00021362304688</h>
			<angle>-1.4967686587314035</angle>
		</robndbox>
		<extra/>
	</object>
   <object>
		<name>small-vehicle</name>
		<pose>Unspecified</pose>
		<truncated>0</truncated>
		<difficult>0</difficult>
		<robndbox>
			<cx>2786.0</cx>
			<cy>1498.0</cy>
			<w>58.00007247924805</w>
			<h>143.00015258789062</h>
			<angle>-1.5009833028286579</angle>
		</robndbox>
		<extra/>
	</object>
   <object>
		<name>small-vehicle</name>
		<pose>Unspecified</pose>
		<truncated>0</truncated>
		<difficult>0</difficult>
		<robndbox>
			<cx>3206.0</cx>
			<cy>1551.0</cy>
			<w>62.000091552734375</w>
			<h>145.99996948242188</h>
			<angle>-1.503066218770461</angle>
		</robndbox>
		<extra/>
	</object>
   <object>
		<name>small-vehicle</name>
		<pose>Unspecified</pose>
		<truncated>0</truncated>
		<difficult>0</difficult>
		<robndbox>
			<cx>3634.0</cx>
			<cy>1568.0</cy>
			<w>56.99998474121094</w>
			<h>148.00013732910156</h>
			<angle>-1.5022986959462903</angle>
		</robndbox>
		<extra/>
	</object>
  </annotation>
