<annotation>
	<folder>train</folder>
	<filename>DJI_20220405105332_0015_frame_1800.png</filename>
	<path>C:\Users\realt\AI\DroneTruth\train\DJI_20220405105332_0015_frame_1800.png</path>
	<source>
		<database>Unknown</database>
	</source>
	<size>
		<width>3840</width>
		<height>2160</height>
		<depth>3</depth>
	</size>
	<segmented>0</segmented>
	<object>
		<name>small-vehicle</name>
		<pose>Unspecified</pose>
		<truncated>0</truncated>
		<difficult>0</difficult>
		<robndbox>
			<cx>525.0</cx>
			<cy>875.0</cy>
			<w>57.0</w>
			<h>122.0</h>
			<angle>5.205006</angle>
		</robndbox>
		<extra/>
	</object>
	<object>
		<name>small-vehicle</name>
		<pose>Unspecified</pose>
		<truncated>0</truncated>
		<difficult>0</difficult>
		<robndbox>
			<cx>672.0</cx>
			<cy>958.0</cy>
			<w>62.0</w>
			<h>135.0</h>
			<angle>5.206386</angle>
		</robndbox>
		<extra/>
	</object>
	<object>
		<name>small-vehicle</name>
		<pose>Unspecified</pose>
		<truncated>0</truncated>
		<difficult>0</difficult>
		<robndbox>
			<cx>271.0</cx>
			<cy>1296.0</cy>
			<w>61.0</w>
			<h>151.0</h>
			<angle>0.780587</angle>
		</robndbox>
		<extra/>
	</object>
	<object>
		<name>small-vehicle</name>
		<pose>Unspecified</pose>
		<truncated>0</truncated>
		<difficult>0</difficult>
		<robndbox>
			<cx>165.0</cx>
			<cy>1291.0</cy>
			<w>62.0</w>
			<h>152.0</h>
			<angle>0.58896</angle>
		</robndbox>
		<extra/>
	</object>
	<object>
		<name>small-vehicle</name>
		<pose>Unspecified</pose>
		<truncated>0</truncated>
		<difficult>0</difficult>
		<robndbox>
			<cx>805.0</cx>
			<cy>1492.0</cy>
			<w>58.9999</w>
			<h>160.0</h>
			<angle>1.584124</angle>
		</robndbox>
		<extra/>
	</object>
	<object>
		<name>large-vehicle</name>
		<pose>Unspecified</pose>
		<truncated>0</truncated>
		<difficult>0</difficult>
		<robndbox>
			<cx>1118.0</cx>
			<cy>830.0</cy>
			<w>69.9999</w>
			<h>175.0</h>
			<angle>5.904623</angle>
		</robndbox>
		<extra/>
	</object>
	<object>
		<name>small-vehicle</name>
		<pose>Unspecified</pose>
		<truncated>0</truncated>
		<difficult>0</difficult>
		<robndbox>
			<cx>1405.0</cx>
			<cy>1203.0</cy>
			<w>60.0001</w>
			<h>134.0</h>
			<angle>5.263214</angle>
		</robndbox>
		<extra/>
	</object>
	<object>
		<name>large-vehicle</name>
		<pose>Unspecified</pose>
		<truncated>0</truncated>
		<difficult>0</difficult>
		<robndbox>
			<cx>1990.0</cx>
			<cy>1303.0</cy>
			<w>67.0</w>
			<h>226.0001</h>
			<angle>4.729842</angle>
		</robndbox>
		<extra/>
	</object>
	<object>
		<name>small-vehicle</name>
		<pose>Unspecified</pose>
		<truncated>0</truncated>
		<difficult>0</difficult>
		<robndbox>
			<cx>2229.0</cx>
			<cy>1299.0</cy>
			<w>56.0</w>
			<h>136.0001</h>
			<angle>4.735252</angle>
		</robndbox>
		<extra/>
	</object>
	<object>
		<name>small-vehicle</name>
		<pose>Unspecified</pose>
		<truncated>0</truncated>
		<difficult>0</difficult>
		<robndbox>
			<cx>2422.0</cx>
			<cy>1310.0</cy>
			<w>60.0</w>
			<h>149.0</h>
			<angle>4.731337</angle>
		</robndbox>
		<extra/>
	</object>
	<object>
		<name>small-vehicle</name>
		<pose>Unspecified</pose>
		<truncated>0</truncated>
		<difficult>0</difficult>
		<robndbox>
			<cx>2651.0</cx>
			<cy>1404.0</cy>
			<w>58.0</w>
			<h>150.0001</h>
			<angle>4.694935</angle>
		</robndbox>
		<extra/>
	</object>
	<object>
		<name>small-vehicle</name>
		<pose>Unspecified</pose>
		<truncated>0</truncated>
		<difficult>0</difficult>
		<robndbox>
			<cx>3259.0</cx>
			<cy>1362.0</cy>
			<w>58.0</w>
			<h>150.0001</h>
			<angle>4.694935</angle>
		</robndbox>
		<extra/>
	</object>
	<object>
		<name>small-vehicle</name>
		<pose>Unspecified</pose>
		<truncated>0</truncated>
		<difficult>0</difficult>
		<robndbox>
			<cx>127.0</cx>
			<cy>1671.0</cy>
			<w>60.9999</w>
			<h>138.0001</h>
			<angle>2.306236</angle>
		</robndbox>
		<extra/>
	</object>
	<object>
		<name>small-vehicle</name>
		<pose>Unspecified</pose>
		<truncated>0</truncated>
		<difficult>0</difficult>
		<robndbox>
			<cx>362.0</cx>
			<cy>1654.0</cy>
			<w>60.0</w>
			<h>146.0001</h>
			<angle>2.820039</angle>
		</robndbox>
		<extra/>
	</object>
	<object>
		<name>small-vehicle</name>
		<pose>Unspecified</pose>
		<truncated>0</truncated>
		<difficult>0</difficult>
		<robndbox>
			<cx>506.0</cx>
			<cy>1653.0</cy>
			<w>57.0</w>
			<h>119.0001</h>
			<angle>2.996646</angle>
		</robndbox>
		<extra/>
	</object>
	<object>
		<name>small-vehicle</name>
		<pose>Unspecified</pose>
		<truncated>0</truncated>
		<difficult>0</difficult>
		<robndbox>
			<cx>918.0</cx>
			<cy>1669.0</cy>
			<w>58.0</w>
			<h>123.0</h>
			<angle>2.700449</angle>
		</robndbox>
		<extra/>
	</object>
	<object>
		<name>small-vehicle</name>
		<pose>Unspecified</pose>
		<truncated>0</truncated>
		<difficult>0</difficult>
		<robndbox>
			<cx>1373.0</cx>
			<cy>1667.0</cy>
			<w>65.0001</w>
			<h>158.0001</h>
			<angle>2.548181</angle>
		</robndbox>
		<extra/>
	</object>
	<object>
		<name>small-vehicle</name>
		<pose>Unspecified</pose>
		<truncated>0</truncated>
		<difficult>0</difficult>
		<robndbox>
			<cx>1765.0</cx>
			<cy>1955.0</cy>
			<w>60.0001</w>
			<h>148.0</h>
			<angle>2.418203</angle>
		</robndbox>
		<extra/>
	</object>
	<object>
		<name>small-vehicle</name>
		<pose>Unspecified</pose>
		<truncated>0</truncated>
		<difficult>0</difficult>
		<robndbox>
			<cx>1766.0</cx>
			<cy>2085.0</cy>
			<w>60.0001</w>
			<h>145.0001</h>
			<angle>2.260704</angle>
		</robndbox>
		<extra/>
	</object>
	<object>
		<name>small-vehicle</name>
		<pose>Unspecified</pose>
		<truncated>0</truncated>
		<difficult>0</difficult>
		<robndbox>
			<cx>3201.0</cx>
			<cy>1648.0</cy>
			<w>59.0</w>
			<h>130.0002</h>
			<angle>1.593571</angle>
		</robndbox>
		<extra/>
	</object>
	<object>
		<name>small-vehicle</name>
		<pose>Unspecified</pose>
		<truncated>0</truncated>
		<difficult>0</difficult>
		<robndbox>
			<cx>3023.0</cx>
			<cy>1641.0</cy>
			<w>58.0</w>
			<h>143.0</h>
			<angle>1.588249</angle>
		</robndbox>
		<extra/>
	</object>
	<object>
		<name>small-vehicle</name>
		<pose>Unspecified</pose>
		<truncated>0</truncated>
		<difficult>0</difficult>
		<robndbox>
			<cx>2852.0</cx>
			<cy>1640.0</cy>
			<w>57.0</w>
			<h>149.9999</h>
			<angle>1.555685</angle>
		</robndbox>
		<extra/>
	</object>
	<object>
		<name>small-vehicle</name>
		<pose>Unspecified</pose>
		<truncated>0</truncated>
		<difficult>0</difficult>
		<robndbox>
			<cx>2692.0</cx>
			<cy>1634.0</cy>
			<w>52.0</w>
			<h>124.0</h>
			<angle>1.570796</angle>
		</robndbox>
		<extra/>
	</object>
	<object>
		<name>small-vehicle</name>
		<pose>Unspecified</pose>
		<truncated>0</truncated>
		<difficult>0</difficult>
		<robndbox>
			<cx>2514.0</cx>
			<cy>1622.0</cy>
			<w>57.0</w>
			<h>137.0</h>
			<angle>1.58825</angle>
		</robndbox>
		<extra/>
	</object>
	<object>
		<name>small-vehicle</name>
		<pose>Unspecified</pose>
		<truncated>0</truncated>
		<difficult>0</difficult>
		<robndbox>
			<cx>2357.0</cx>
			<cy>1613.0</cy>
			<w>58.0</w>
			<h>126.0001</h>
			<angle>1.588249</angle>
		</robndbox>
		<extra/>
	</object>
	<object>
		<name>small-vehicle</name>
		<pose>Unspecified</pose>
		<truncated>0</truncated>
		<difficult>0</difficult>
		<robndbox>
			<cx>2211.0</cx>
			<cy>1622.0</cy>
			<w>58.0001</w>
			<h>122.0001</h>
			<angle>1.584125</angle>
		</robndbox>
		<extra/>
	</object>
	<object>
		<name>small-vehicle</name>
		<pose>Unspecified</pose>
		<truncated>0</truncated>
		<difficult>0</difficult>
		<robndbox>
			<cx>1049.0</cx>
			<cy>476.0</cy>
			<w>60.0</w>
			<h>111.0</h>
			<angle>0.034907</angle>
		</robndbox>
		<extra/>
	</object>
	<object>
		<name>small-vehicle</name>
		<pose>Unspecified</pose>
		<truncated>0</truncated>
		<difficult>0</difficult>
		<robndbox>
			<cx>1090.0</cx>
			<cy>307.0</cy>
			<w>63.0</w>
			<h>141.0</h>
			<angle>0.374799</angle>
		</robndbox>
		<extra/>
	</object>
	<object>
		<name>small-vehicle</name>
		<pose>Unspecified</pose>
		<truncated>0</truncated>
		<difficult>0</difficult>
		<robndbox>
			<cx>306.0</cx>
			<cy>192.0</cy>
			<w>64.0</w>
			<h>141.0</h>
			<angle>1.000247</angle>
		</robndbox>
		<extra/>
	</object>
	<object>
		<name>small-vehicle</name>
		<pose>Unspecified</pose>
		<truncated>0</truncated>
		<difficult>0</difficult>
		<robndbox>
			<cx>161.0</cx>
			<cy>287.0</cy>
			<w>65.0</w>
			<h>148.0</h>
			<angle>1.019141</angle>
		</robndbox>
		<extra/>
	</object>
	<object>
		<name>small-vehicle</name>
		<pose>Unspecified</pose>
		<truncated>0</truncated>
		<difficult>0</difficult>
		<robndbox>
			<cx>491.0</cx>
			<cy>68.0</cy>
			<w>62.0</w>
			<h>130.0</h>
			<angle>0.948874</angle>
		</robndbox>
		<extra/>
	</object>
	<object>
		<name>small-vehicle</name>
		<pose>Unspecified</pose>
		<truncated>0</truncated>
		<difficult>0</difficult>
		<robndbox>
			<cx>384.4367</cx>
			<cy>806.4982</cy>
			<w>56.0285</w>
			<h>131.321</h>
			<angle>5.115006</angle>
		</robndbox>
		<extra/>
	</object>
	<object>
		<name>two-wheeler</name>
		<pose>Unspecified</pose>
		<truncated>0</truncated>
		<difficult>0</difficult>
		<robndbox>
			<cx>2838.932</cx>
			<cy>1713.5</cy>
			<w>30.0</w>
			<h>67.0</h>
			<angle>0.0</angle>
		</robndbox>
		<extra/>
	</object>
	<object>
		<name>two-wheeler</name>
		<pose>Unspecified</pose>
		<truncated>0</truncated>
		<difficult>0</difficult>
		<robndbox>
			<cx>2673.932</cx>
			<cy>1814.5</cy>
			<w>30.0</w>
			<h>67.0</h>
			<angle>1.5</angle>
		</robndbox>
		<extra/>
	</object>
</annotation>
