   <annotation>
	<folder>train</folder>
	<filename>DJI_20220405123814_0008_frame_0.png</filename>
	<path>C:\Users\realt\AI\DroneTruth\train\DJI_20220405123814_0008_frame_0.png</path>
	<source>
		<database>DroneTruth</database>
	</source>
	<size>
		<width>3840</width>
		<height>2160</height>
		<depth>3</depth>
	</size>
	<segmented>0</segmented>
       <object>
		<name>large-vehicle</name>
		<pose>Unspecified</pose>
		<truncated>0</truncated>
		<difficult>0</difficult>
		<robndbox>
			<cx>85.0</cx>
			<cy>1590.0</cy>
			<w>84.00001525878906</w>
			<h>156.0000457763672</h>
			<angle>2.5598289023026943</angle>
		</robndbox>
		<extra/>
	</object>
   <object>
		<name>small-vehicle</name>
		<pose>Unspecified</pose>
		<truncated>0</truncated>
		<difficult>0</difficult>
		<robndbox>
			<cx>340.0</cx>
			<cy>1561.0</cy>
			<w>70.99996948242188</w>
			<h>141.0</h>
			<angle>-0.7502368774282636</angle>
		</robndbox>
		<extra/>
	</object>
   <object>
		<name>small-vehicle</name>
		<pose>Unspecified</pose>
		<truncated>0</truncated>
		<difficult>0</difficult>
		<robndbox>
			<cx>463.0</cx>
			<cy>1559.0</cy>
			<w>79.00005340576172</w>
			<h>172.0000762939453</h>
			<angle>2.319174579827086</angle>
		</robndbox>
		<extra/>
	</object>
   <object>
		<name>small-vehicle</name>
		<pose>Unspecified</pose>
		<truncated>0</truncated>
		<difficult>0</difficult>
		<robndbox>
			<cx>589.0</cx>
			<cy>1561.0</cy>
			<w>67.00004577636719</w>
			<h>146.00003051757812</h>
			<angle>2.399855763462734</angle>
		</robndbox>
		<extra/>
	</object>
   <object>
		<name>small-vehicle</name>
		<pose>Unspecified</pose>
		<truncated>0</truncated>
		<difficult>0</difficult>
		<robndbox>
			<cx>689.0</cx>
			<cy>1558.0</cy>
			<w>69.99996948242188</w>
			<h>148.0</h>
			<angle>2.474286745921286</angle>
		</robndbox>
		<extra/>
	</object>
   <object>
		<name>small-vehicle</name>
		<pose>Unspecified</pose>
		<truncated>0</truncated>
		<difficult>0</difficult>
		<robndbox>
			<cx>811.0</cx>
			<cy>1556.0</cy>
			<w>66.99999237060547</w>
			<h>158.00003051757812</h>
			<angle>-0.738242128116021</angle>
		</robndbox>
		<extra/>
	</object>
   <object>
		<name>small-vehicle</name>
		<pose>Unspecified</pose>
		<truncated>0</truncated>
		<difficult>0</difficult>
		<robndbox>
			<cx>914.0</cx>
			<cy>1561.0</cy>
			<w>61.99998092651367</w>
			<h>135.9999542236328</h>
			<angle>2.3457234326977243</angle>
		</robndbox>
		<extra/>
	</object>
   <object>
		<name>small-vehicle</name>
		<pose>Unspecified</pose>
		<truncated>0</truncated>
		<difficult>0</difficult>
		<robndbox>
			<cx>1015.0</cx>
			<cy>1546.0</cy>
			<w>70.00003051757812</w>
			<h>160.00001525878906</h>
			<angle>2.3738917022106745</angle>
		</robndbox>
		<extra/>
	</object>
   <object>
		<name>small-vehicle</name>
		<pose>Unspecified</pose>
		<truncated>0</truncated>
		<difficult>0</difficult>
		<robndbox>
			<cx>1134.0</cx>
			<cy>1548.0</cy>
			<w>69.0</w>
			<h>144.00003051757812</h>
			<angle>2.6561414505047396</angle>
		</robndbox>
		<extra/>
	</object>
   <object>
		<name>small-vehicle</name>
		<pose>Unspecified</pose>
		<truncated>0</truncated>
		<difficult>0</difficult>
		<robndbox>
			<cx>1245.0</cx>
			<cy>1546.0</cy>
			<w>69.00004577636719</w>
			<h>159.00009155273438</h>
			<angle>-0.7206120361054332</angle>
		</robndbox>
		<extra/>
	</object>
   <object>
		<name>small-vehicle</name>
		<pose>Unspecified</pose>
		<truncated>0</truncated>
		<difficult>0</difficult>
		<robndbox>
			<cx>1362.0</cx>
			<cy>1548.0</cy>
			<w>65.9999771118164</w>
			<h>146.0001678466797</h>
			<angle>-0.7683679509532441</angle>
		</robndbox>
		<extra/>
	</object>
   <object>
		<name>small-vehicle</name>
		<pose>Unspecified</pose>
		<truncated>0</truncated>
		<difficult>0</difficult>
		<robndbox>
			<cx>1463.0</cx>
			<cy>1533.0</cy>
			<w>69.00008392333984</w>
			<h>152.0</h>
			<angle>-0.5477685443066198</angle>
		</robndbox>
		<extra/>
	</object>
   <object>
		<name>small-vehicle</name>
		<pose>Unspecified</pose>
		<truncated>0</truncated>
		<difficult>0</difficult>
		<robndbox>
			<cx>1583.0</cx>
			<cy>1539.0</cy>
			<w>61.00004959106445</w>
			<h>132.00006103515625</h>
			<angle>2.4882139422795833</angle>
		</robndbox>
		<extra/>
	</object>
   <object>
		<name>small-vehicle</name>
		<pose>Unspecified</pose>
		<truncated>0</truncated>
		<difficult>0</difficult>
		<robndbox>
			<cx>1694.0</cx>
			<cy>1546.0</cy>
			<w>63.99998092651367</w>
			<h>147.0</h>
			<angle>2.4285324702164695</angle>
		</robndbox>
		<extra/>
	</object>
   <object>
		<name>small-vehicle</name>
		<pose>Unspecified</pose>
		<truncated>0</truncated>
		<difficult>0</difficult>
		<robndbox>
			<cx>1820.0</cx>
			<cy>1546.0</cy>
			<w>61.99992752075195</w>
			<h>136.0000457763672</h>
			<angle>2.3640276555319724</angle>
		</robndbox>
		<extra/>
	</object>
   <object>
		<name>small-vehicle</name>
		<pose>Unspecified</pose>
		<truncated>0</truncated>
		<difficult>0</difficult>
		<robndbox>
			<cx>1927.0</cx>
			<cy>1538.0</cy>
			<w>66.00003051757812</w>
			<h>163.0</h>
			<angle>2.3779304402203465</angle>
		</robndbox>
		<extra/>
	</object>
   <object>
		<name>small-vehicle</name>
		<pose>Unspecified</pose>
		<truncated>0</truncated>
		<difficult>0</difficult>
		<robndbox>
			<cx>2037.0</cx>
			<cy>1530.0</cy>
			<w>67.00001525878906</w>
			<h>162.99996948242188</h>
			<angle>2.3954755283274074</angle>
		</robndbox>
		<extra/>
	</object>
   <object>
		<name>small-vehicle</name>
		<pose>Unspecified</pose>
		<truncated>0</truncated>
		<difficult>0</difficult>
		<robndbox>
			<cx>2184.0</cx>
			<cy>1528.0</cy>
			<w>74.00010681152344</w>
			<h>182.0001220703125</h>
			<angle>2.260596007367058</angle>
		</robndbox>
		<extra/>
	</object>
   <object>
		<name>small-vehicle</name>
		<pose>Unspecified</pose>
		<truncated>0</truncated>
		<difficult>0</difficult>
		<robndbox>
			<cx>2762.0</cx>
			<cy>1518.0</cy>
			<w>67.00007629394531</w>
			<h>163.0000457763672</h>
			<angle>2.410606741897511</angle>
		</robndbox>
		<extra/>
	</object>
   <object>
		<name>small-vehicle</name>
		<pose>Unspecified</pose>
		<truncated>0</truncated>
		<difficult>0</difficult>
		<robndbox>
			<cx>2869.0</cx>
			<cy>1516.0</cy>
			<w>63.00001525878906</w>
			<h>141.00025939941406</h>
			<angle>2.5080760023034374</angle>
		</robndbox>
		<extra/>
	</object>
   <object>
		<name>small-vehicle</name>
		<pose>Unspecified</pose>
		<truncated>0</truncated>
		<difficult>0</difficult>
		<robndbox>
			<cx>2993.0</cx>
			<cy>1520.0</cy>
			<w>59.99995422363281</w>
			<h>156.00003051757812</h>
			<angle>-0.7397675581999484</angle>
		</robndbox>
		<extra/>
	</object>
   <object>
		<name>small-vehicle</name>
		<pose>Unspecified</pose>
		<truncated>0</truncated>
		<difficult>0</difficult>
		<robndbox>
			<cx>3103.0</cx>
			<cy>1517.0</cy>
			<w>70.0000991821289</w>
			<h>157.00001525878906</h>
			<angle>-0.6792222628041007</angle>
		</robndbox>
		<extra/>
	</object>
   <object>
		<name>small-vehicle</name>
		<pose>Unspecified</pose>
		<truncated>0</truncated>
		<difficult>0</difficult>
		<robndbox>
			<cx>3205.0</cx>
			<cy>1510.0</cy>
			<w>64.99998092651367</w>
			<h>155.00003051757812</h>
			<angle>2.388293586375666</angle>
		</robndbox>
		<extra/>
	</object>
   <object>
		<name>small-vehicle</name>
		<pose>Unspecified</pose>
		<truncated>0</truncated>
		<difficult>0</difficult>
		<robndbox>
			<cx>3743.0</cx>
			<cy>1406.0</cy>
			<w>64.99992370605469</w>
			<h>164.00006103515625</h>
			<angle>1.6198365970393132</angle>
		</robndbox>
		<extra/>
	</object>
   <object>
		<name>small-vehicle</name>
		<pose>Unspecified</pose>
		<truncated>0</truncated>
		<difficult>0</difficult>
		<robndbox>
			<cx>3744.0</cx>
			<cy>1198.0</cy>
			<w>63.00006103515625</w>
			<h>144.99989318847656</h>
			<angle>-1.6228328356083501</angle>
		</robndbox>
		<extra/>
	</object>
   <object>
		<name>small-vehicle</name>
		<pose>Unspecified</pose>
		<truncated>0</truncated>
		<difficult>0</difficult>
		<robndbox>
			<cx>3562.0</cx>
			<cy>1201.0</cy>
			<w>58.00004196166992</w>
			<h>130.99986267089844</h>
			<angle>-1.5515681082393857</angle>
		</robndbox>
		<extra/>
	</object>
   <object>
		<name>small-vehicle</name>
		<pose>Unspecified</pose>
		<truncated>0</truncated>
		<difficult>0</difficult>
		<robndbox>
			<cx>3397.0</cx>
			<cy>1204.0</cy>
			<w>60.000022888183594</w>
			<h>147.99990844726562</h>
			<angle>-1.560592887387788</angle>
		</robndbox>
		<extra/>
	</object>
   <object>
		<name>small-vehicle</name>
		<pose>Unspecified</pose>
		<truncated>0</truncated>
		<difficult>0</difficult>
		<robndbox>
			<cx>3232.0</cx>
			<cy>1210.0</cy>
			<w>58.999977111816406</w>
			<h>142.99986267089844</h>
			<angle>-1.5778386455151014</angle>
		</robndbox>
		<extra/>
	</object>
   <object>
		<name>small-vehicle</name>
		<pose>Unspecified</pose>
		<truncated>0</truncated>
		<difficult>0</difficult>
		<robndbox>
			<cx>3064.0</cx>
			<cy>1212.0</cy>
			<w>61.999961853027344</w>
			<h>145.0001983642578</h>
			<angle>-1.591554854274928</angle>
		</robndbox>
		<extra/>
	</object>
   <object>
		<name>small-vehicle</name>
		<pose>Unspecified</pose>
		<truncated>0</truncated>
		<difficult>0</difficult>
		<robndbox>
			<cx>2902.0</cx>
			<cy>1300.0</cy>
			<w>62.0</w>
			<h>157.0</h>
			<angle>-1.5707963267948966</angle>
		</robndbox>
		<extra/>
	</object>
   <object>
		<name>small-vehicle</name>
		<pose>Unspecified</pose>
		<truncated>0</truncated>
		<difficult>0</difficult>
		<robndbox>
			<cx>2463.0</cx>
			<cy>1296.0</cy>
			<w>66.00006866455078</w>
			<h>162.00001525878906</h>
			<angle>-1.6018420607567863</angle>
		</robndbox>
		<extra/>
	</object>
   <object>
		<name>small-vehicle</name>
		<pose>Unspecified</pose>
		<truncated>0</truncated>
		<difficult>0</difficult>
		<robndbox>
			<cx>1917.0</cx>
			<cy>1224.0</cy>
			<w>62.00000762939453</w>
			<h>159.00006103515625</h>
			<angle>-1.5897817148548408</angle>
		</robndbox>
		<extra/>
	</object>
   <object>
		<name>small-vehicle</name>
		<pose>Unspecified</pose>
		<truncated>0</truncated>
		<difficult>0</difficult>
		<robndbox>
			<cx>1745.0</cx>
			<cy>1226.0</cy>
			<w>62.00007247924805</w>
			<h>165.00013732910156</h>
			<angle>-1.595181536328443</angle>
		</robndbox>
		<extra/>
	</object>
   <object>
		<name>small-vehicle</name>
		<pose>Unspecified</pose>
		<truncated>0</truncated>
		<difficult>0</difficult>
		<robndbox>
			<cx>1566.0</cx>
			<cy>1234.0</cy>
			<w>59.0</w>
			<h>148.0</h>
			<angle>-1.5707963267948966</angle>
		</robndbox>
		<extra/>
	</object>
   <object>
		<name>small-vehicle</name>
		<pose>Unspecified</pose>
		<truncated>0</truncated>
		<difficult>0</difficult>
		<robndbox>
			<cx>1377.0</cx>
			<cy>1231.0</cy>
			<w>65.99999237060547</w>
			<h>157.0001220703125</h>
			<angle>-1.59954314950064</angle>
		</robndbox>
		<extra/>
	</object>
   <object>
		<name>small-vehicle</name>
		<pose>Unspecified</pose>
		<truncated>0</truncated>
		<difficult>0</difficult>
		<robndbox>
			<cx>1179.0</cx>
			<cy>1235.0</cy>
			<w>64.99995803833008</w>
			<h>166.00001525878906</h>
			<angle>-1.579887362080109</angle>
		</robndbox>
		<extra/>
	</object>
   <object>
		<name>small-vehicle</name>
		<pose>Unspecified</pose>
		<truncated>0</truncated>
		<difficult>0</difficult>
		<robndbox>
			<cx>256.0</cx>
			<cy>1317.0</cy>
			<w>64.0</w>
			<h>171.0</h>
			<angle>-1.5707963267948966</angle>
		</robndbox>
		<extra/>
	</object>
   <object>
		<name>small-vehicle</name>
		<pose>Unspecified</pose>
		<truncated>0</truncated>
		<difficult>0</difficult>
		<robndbox>
			<cx>2367.0</cx>
			<cy>920.0</cy>
			<w>65.00004577636719</w>
			<h>159.00003051757812</h>
			<angle>2.99301392234358</angle>
		</robndbox>
		<extra/>
	</object>
   <object>
		<name>small-vehicle</name>
		<pose>Unspecified</pose>
		<truncated>0</truncated>
		<difficult>0</difficult>
		<robndbox>
			<cx>2339.0</cx>
			<cy>730.0</cy>
			<w>61.99988555908203</w>
			<h>137.0000457763672</h>
			<angle>3.0199731106099765</angle>
		</robndbox>
		<extra/>
	</object>
   <object>
		<name>small-vehicle</name>
		<pose>Unspecified</pose>
		<truncated>0</truncated>
		<difficult>0</difficult>
		<robndbox>
			<cx>2308.0</cx>
			<cy>559.0</cy>
			<w>58.99995803833008</w>
			<h>150.00001525878906</h>
			<angle>2.9874198040959183</angle>
		</robndbox>
		<extra/>
	</object>
   <object>
		<name>small-vehicle</name>
		<pose>Unspecified</pose>
		<truncated>0</truncated>
		<difficult>0</difficult>
		<robndbox>
			<cx>2280.0</cx>
			<cy>393.0</cy>
			<w>62.000179290771484</w>
			<h>156.00006103515625</h>
			<angle>2.95367216835399</angle>
		</robndbox>
		<extra/>
	</object>
   <object>
		<name>small-vehicle</name>
		<pose>Unspecified</pose>
		<truncated>0</truncated>
		<difficult>0</difficult>
		<robndbox>
			<cx>2242.0</cx>
			<cy>225.0</cy>
			<w>66.99990844726562</w>
			<h>163.0000457763672</h>
			<angle>2.9556773872194873</angle>
		</robndbox>
		<extra/>
	</object>
   <object>
		<name>small-vehicle</name>
		<pose>Unspecified</pose>
		<truncated>0</truncated>
		<difficult>0</difficult>
		<robndbox>
			<cx>2150.0</cx>
			<cy>880.0</cy>
			<w>63.000144958496094</w>
			<h>147.00006103515625</h>
			<angle>-2.615240210680502</angle>
		</robndbox>
		<extra/>
	</object>
   <object>
		<name>small-vehicle</name>
		<pose>Unspecified</pose>
		<truncated>0</truncated>
		<difficult>0</difficult>
		<robndbox>
			<cx>2119.0</cx>
			<cy>787.0</cy>
			<w>61.0000114440918</w>
			<h>158.00003051757812</h>
			<angle>-2.3922147787519377</angle>
		</robndbox>
		<extra/>
	</object>
   <object>
		<name>small-vehicle</name>
		<pose>Unspecified</pose>
		<truncated>0</truncated>
		<difficult>0</difficult>
		<robndbox>
			<cx>2101.0</cx>
			<cy>693.0</cy>
			<w>64.00008392333984</w>
			<h>161.99996948242188</h>
			<angle>-2.3518277057219388</angle>
		</robndbox>
		<extra/>
	</object>
   <object>
		<name>small-vehicle</name>
		<pose>Unspecified</pose>
		<truncated>0</truncated>
		<difficult>0</difficult>
		<robndbox>
			<cx>2071.0</cx>
			<cy>604.0</cy>
			<w>65.99998474121094</w>
			<h>169.99998474121094</h>
			<angle>-2.424979599990392</angle>
		</robndbox>
		<extra/>
	</object>
   <object>
		<name>small-vehicle</name>
		<pose>Unspecified</pose>
		<truncated>0</truncated>
		<difficult>0</difficult>
		<robndbox>
			<cx>2055.0</cx>
			<cy>484.0</cy>
			<w>62.000022888183594</w>
			<h>157.99996948242188</h>
			<angle>-2.4346847652642554</angle>
		</robndbox>
		<extra/>
	</object>
   <object>
		<name>small-vehicle</name>
		<pose>Unspecified</pose>
		<truncated>0</truncated>
		<difficult>0</difficult>
		<robndbox>
			<cx>2045.0</cx>
			<cy>370.0</cy>
			<w>61.00006103515625</w>
			<h>151.00010681152344</h>
			<angle>-2.3468043917009394</angle>
		</robndbox>
		<extra/>
	</object>
   <object>
		<name>small-vehicle</name>
		<pose>Unspecified</pose>
		<truncated>0</truncated>
		<difficult>0</difficult>
		<robndbox>
			<cx>2046.0</cx>
			<cy>257.0</cy>
			<w>67.0</w>
			<h>153.99996948242188</h>
			<angle>-2.457696538166171</angle>
		</robndbox>
		<extra/>
	</object>
   <object>
		<name>small-vehicle</name>
		<pose>Unspecified</pose>
		<truncated>0</truncated>
		<difficult>0</difficult>
		<robndbox>
			<cx>2005.0</cx>
			<cy>181.0</cy>
			<w>64.00004577636719</w>
			<h>146.99998474121094</h>
			<angle>-2.358615832690676</angle>
		</robndbox>
		<extra/>
	</object>
  </annotation>
