   <annotation>
	<folder>train</folder>
	<filename>DJI_20220218135103_0001_frame_2600.png</filename>
	<path>C:\Users\realt\AI\DroneTruth\train\DJI_20220218135103_0001_frame_2600.png</path>
	<source>
		<database>DroneTruth</database>
	</source>
	<size>
		<width>3840</width>
		<height>2160</height>
		<depth>3</depth>
	</size>
	<segmented>0</segmented>
       <object>
		<name>small-vehicle</name>
		<pose>Unspecified</pose>
		<truncated>0</truncated>
		<difficult>0</difficult>
		<robndbox>
			<cx>674.0</cx>
			<cy>1000.0</cy>
			<w>61.00005340576172</w>
			<h>153.00009155273438</h>
			<angle>1.6421845549104954</angle>
		</robndbox>
		<extra/>
	</object>
   <object>
		<name>small-vehicle</name>
		<pose>Unspecified</pose>
		<truncated>0</truncated>
		<difficult>0</difficult>
		<robndbox>
			<cx>1212.0</cx>
			<cy>1066.0</cy>
			<w>64.00003814697266</w>
			<h>160.00006103515625</h>
			<angle>1.7644361646951117</angle>
		</robndbox>
		<extra/>
	</object>
   <object>
		<name>small-vehicle</name>
		<pose>Unspecified</pose>
		<truncated>0</truncated>
		<difficult>0</difficult>
		<robndbox>
			<cx>1694.0</cx>
			<cy>1406.0</cy>
			<w>62.00003433227539</w>
			<h>153.00003051757812</h>
			<angle>2.2096102392045824</angle>
		</robndbox>
		<extra/>
	</object>
   <object>
		<name>small-vehicle</name>
		<pose>Unspecified</pose>
		<truncated>0</truncated>
		<difficult>0</difficult>
		<robndbox>
			<cx>1982.0</cx>
			<cy>1505.0</cy>
			<w>62.99998474121094</w>
			<h>159.00006103515625</h>
			<angle>2.389339635960328</angle>
		</robndbox>
		<extra/>
	</object>
   <object>
		<name>two-wheeler</name>
		<pose>Unspecified</pose>
		<truncated>0</truncated>
		<difficult>0</difficult>
		<robndbox>
			<cx>2128.0</cx>
			<cy>1742.0</cy>
			<w>30.000167846679688</w>
			<h>77.00001525878906</h>
			<angle>2.6119512595562857</angle>
		</robndbox>
		<extra/>
	</object>
   <object>
		<name>large-vehicle</name>
		<pose>Unspecified</pose>
		<truncated>0</truncated>
		<difficult>0</difficult>
		<robndbox>
			<cx>2546.0</cx>
			<cy>1643.0</cy>
			<w>69.99998474121094</w>
			<h>202.0000762939453</h>
			<angle>-0.5543209220509531</angle>
		</robndbox>
		<extra/>
	</object>
   <object>
		<name>small-vehicle</name>
		<pose>Unspecified</pose>
		<truncated>0</truncated>
		<difficult>0</difficult>
		<robndbox>
			<cx>2312.0</cx>
			<cy>1327.0</cy>
			<w>65.0001220703125</w>
			<h>158.0001678466797</h>
			<angle>-0.7805875001910069</angle>
		</robndbox>
		<extra/>
	</object>
   <object>
		<name>small-vehicle</name>
		<pose>Unspecified</pose>
		<truncated>0</truncated>
		<difficult>0</difficult>
		<robndbox>
			<cx>2042.0</cx>
			<cy>1100.0</cy>
			<w>62.000003814697266</w>
			<h>158.0</h>
			<angle>-0.9849758348504883</angle>
		</robndbox>
		<extra/>
	</object>
   <object>
		<name>two-wheeler</name>
		<pose>Unspecified</pose>
		<truncated>0</truncated>
		<difficult>0</difficult>
		<robndbox>
			<cx>1958.0</cx>
			<cy>846.0</cy>
			<w>25.000078201293945</w>
			<h>58.00009536743164</h>
			<angle>-1.141098698970211</angle>
		</robndbox>
		<extra/>
	</object>
   <object>
		<name>large-vehicle</name>
		<pose>Unspecified</pose>
		<truncated>0</truncated>
		<difficult>0</difficult>
		<robndbox>
			<cx>982.0</cx>
			<cy>638.0</cy>
			<w>95.00003051757812</w>
			<h>331.0000305175781</h>
			<angle>-1.512286276122166</angle>
		</robndbox>
		<extra/>
	</object>
   <object>
		<name>large-vehicle</name>
		<pose>Unspecified</pose>
		<truncated>0</truncated>
		<difficult>0</difficult>
		<robndbox>
			<cx>1277.0</cx>
			<cy>654.0</cy>
			<w>94.00001525878906</w>
			<h>260.0000915527344</h>
			<angle>-1.50527854264016</angle>
		</robndbox>
		<extra/>
	</object>
   <object>
		<name>small-vehicle</name>
		<pose>Unspecified</pose>
		<truncated>0</truncated>
		<difficult>0</difficult>
		<robndbox>
			<cx>232.0</cx>
			<cy>688.0</cy>
			<w>59.999961853027344</w>
			<h>130.0</h>
			<angle>-1.4835297654519062</angle>
		</robndbox>
		<extra/>
	</object>
   <object>
		<name>small-vehicle</name>
		<pose>Unspecified</pose>
		<truncated>0</truncated>
		<difficult>0</difficult>
		<robndbox>
			<cx>2334.0</cx>
			<cy>649.0</cy>
			<w>59.0</w>
			<h>145.9999542236328</h>
			<angle>-2.1991153399594268</angle>
		</robndbox>
		<extra/>
	</object>
   <object>
		<name>small-vehicle</name>
		<pose>Unspecified</pose>
		<truncated>0</truncated>
		<difficult>0</difficult>
		<robndbox>
			<cx>2617.0</cx>
			<cy>385.0</cy>
			<w>60.000057220458984</w>
			<h>126.00013732910156</h>
			<angle>-2.6772034738699686</angle>
		</robndbox>
		<extra/>
	</object>
  </annotation>
