<annotation>
	<folder>train</folder>
	<filename>DJI_20191231173735_0003_frame_6000.png</filename>
	<path>C:\Users\realt\AI\DroneTruth\train\DJI_20191231173735_0003_frame_6000.png</path>
	<source>
		<database>Unknown</database>
	</source>
	<size>
		<width>3840</width>
		<height>2160</height>
		<depth>3</depth>
	</size>
	<segmented>0</segmented>
	<object>
		<name>large-vehicle</name>
		<pose>Unspecified</pose>
		<truncated>0</truncated>
		<difficult>0</difficult>
		<robndbox>
			<cx>1628.0</cx>
			<cy>1247.0</cy>
			<w>74.0</w>
			<h>193.0001</h>
			<angle>3.159046</angle>
		</robndbox>
		<extra/>
	</object>
	<object>
		<name>small-vehicle</name>
		<pose>Unspecified</pose>
		<truncated>0</truncated>
		<difficult>0</difficult>
		<robndbox>
			<cx>2150.0</cx>
			<cy>1644.0</cy>
			<w>62.0001</w>
			<h>152.0002</h>
			<angle>1.543326</angle>
		</robndbox>
		<extra/>
	</object>
	<object>
		<name>small-vehicle</name>
		<pose>Unspecified</pose>
		<truncated>0</truncated>
		<difficult>0</difficult>
		<robndbox>
			<cx>2692.0</cx>
			<cy>1951.0</cy>
			<w>71.0</w>
			<h>163.0001</h>
			<angle>1.793233</angle>
		</robndbox>
		<extra/>
	</object>
	<object>
		<name>small-vehicle</name>
		<pose>Unspecified</pose>
		<truncated>0</truncated>
		<difficult>0</difficult>
		<robndbox>
			<cx>2338.0</cx>
			<cy>1361.0</cy>
			<w>74.0</w>
			<h>179.0</h>
			<angle>0.413238</angle>
		</robndbox>
		<extra/>
	</object>
	<object>
		<name>small-vehicle</name>
		<pose>Unspecified</pose>
		<truncated>0</truncated>
		<difficult>0</difficult>
		<robndbox>
			<cx>2793.0</cx>
			<cy>1375.0</cy>
			<w>69.0</w>
			<h>163.0002</h>
			<angle>5.126421</angle>
		</robndbox>
		<extra/>
	</object>
	<object>
		<name>small-vehicle</name>
		<pose>Unspecified</pose>
		<truncated>0</truncated>
		<difficult>0</difficult>
		<robndbox>
			<cx>1694.0</cx>
			<cy>841.0</cy>
			<w>72.0001</w>
			<h>186.0</h>
			<angle>3.390555</angle>
		</robndbox>
		<extra/>
	</object>
	<object>
		<name>small-vehicle</name>
		<pose>Unspecified</pose>
		<truncated>0</truncated>
		<difficult>0</difficult>
		<robndbox>
			<cx>1799.0</cx>
			<cy>437.0</cy>
			<w>68.0</w>
			<h>172.0</h>
			<angle>3.270503</angle>
		</robndbox>
		<extra/>
	</object>
	<object>
		<name>small-vehicle</name>
		<pose>Unspecified</pose>
		<truncated>0</truncated>
		<difficult>0</difficult>
		<robndbox>
			<cx>2564.0</cx>
			<cy>806.0</cy>
			<w>76.9999</w>
			<h>196.0001</h>
			<angle>5.440157</angle>
		</robndbox>
		<extra/>
	</object>
	<object>
		<name>small-vehicle</name>
		<pose>Unspecified</pose>
		<truncated>0</truncated>
		<difficult>0</difficult>
		<robndbox>
			<cx>2722.0</cx>
			<cy>978.0</cy>
			<w>71.0001</w>
			<h>167.0001</h>
			<angle>5.511995</angle>
		</robndbox>
		<extra/>
	</object>
	<object>
		<name>small-vehicle</name>
		<pose>Unspecified</pose>
		<truncated>0</truncated>
		<difficult>0</difficult>
		<robndbox>
			<cx>2861.0</cx>
			<cy>1120.0</cy>
			<w>78.0</w>
			<h>205.0</h>
			<angle>5.431313</angle>
		</robndbox>
		<extra/>
	</object>
	<object>
		<name>small-vehicle</name>
		<pose>Unspecified</pose>
		<truncated>0</truncated>
		<difficult>0</difficult>
		<robndbox>
			<cx>3003.0</cx>
			<cy>1254.0</cy>
			<w>76.0</w>
			<h>185.9999</h>
			<angle>5.521257</angle>
		</robndbox>
		<extra/>
	</object>
	<object>
		<name>small-vehicle</name>
		<pose>Unspecified</pose>
		<truncated>0</truncated>
		<difficult>0</difficult>
		<robndbox>
			<cx>749.0</cx>
			<cy>188.0</cy>
			<w>63.0</w>
			<h>147.0</h>
			<angle>1.879971</angle>
		</robndbox>
		<extra/>
	</object>
</annotation>
