   <annotation>
	<folder>train</folder>
	<filename>DJI_20191231173735_0003_frame_7400.png</filename>
	<path>C:\Users\realt\AI\DroneTruth\train\DJI_20191231173735_0003_frame_7400.png</path>
	<source>
		<database>DroneTruth</database>
	</source>
	<size>
		<width>3840</width>
		<height>2160</height>
		<depth>3</depth>
	</size>
	<segmented>0</segmented>
       <object>
		<name>small-vehicle</name>
		<pose>Unspecified</pose>
		<truncated>0</truncated>
		<difficult>0</difficult>
		<robndbox>
			<cx>2561.0</cx>
			<cy>806.0</cy>
			<w>76.99998474121094</w>
			<h>196.00003051757812</h>
			<angle>-0.8315920553136388</angle>
		</robndbox>
		<extra/>
	</object>
   <object>
		<name>small-vehicle</name>
		<pose>Unspecified</pose>
		<truncated>0</truncated>
		<difficult>0</difficult>
		<robndbox>
			<cx>2720.0</cx>
			<cy>975.0</cy>
			<w>71.00004577636719</w>
			<h>166.99993896484375</h>
			<angle>-0.7750189011290071</angle>
		</robndbox>
		<extra/>
	</object>
   <object>
		<name>small-vehicle</name>
		<pose>Unspecified</pose>
		<truncated>0</truncated>
		<difficult>0</difficult>
		<robndbox>
			<cx>2859.0</cx>
			<cy>1119.0</cy>
			<w>78.00009155273438</w>
			<h>207.99996948242188</h>
			<angle>-0.8486047319046662</angle>
		</robndbox>
		<extra/>
	</object>
   <object>
		<name>small-vehicle</name>
		<pose>Unspecified</pose>
		<truncated>0</truncated>
		<difficult>0</difficult>
		<robndbox>
			<cx>3002.0</cx>
			<cy>1252.0</cy>
			<w>79.00006103515625</w>
			<h>186.00006103515625</h>
			<angle>-0.7632694075326236</angle>
		</robndbox>
		<extra/>
	</object>
   <object>
		<name>small-vehicle</name>
		<pose>Unspecified</pose>
		<truncated>0</truncated>
		<difficult>0</difficult>
		<robndbox>
			<cx>3178.0</cx>
			<cy>1703.0</cy>
			<w>65.99996948242188</w>
			<h>172.9999237060547</h>
			<angle>1.6231558025231527</angle>
		</robndbox>
		<extra/>
	</object>
   <object>
		<name>small-vehicle</name>
		<pose>Unspecified</pose>
		<truncated>0</truncated>
		<difficult>0</difficult>
		<robndbox>
			<cx>3632.0</cx>
			<cy>1591.0</cy>
			<w>74.00003814697266</w>
			<h>175.99998474121094</h>
			<angle>-1.6057029854570506</angle>
		</robndbox>
		<extra/>
	</object>
   <object>
		<name>small-vehicle</name>
		<pose>Unspecified</pose>
		<truncated>0</truncated>
		<difficult>0</difficult>
		<robndbox>
			<cx>1285.0</cx>
			<cy>1398.0</cy>
			<w>69.99996948242188</w>
			<h>179.99998474121094</h>
			<angle>-2.3004411514136542</angle>
		</robndbox>
		<extra/>
	</object>
   <object>
		<name>small-vehicle</name>
		<pose>Unspecified</pose>
		<truncated>0</truncated>
		<difficult>0</difficult>
		<robndbox>
			<cx>854.0</cx>
			<cy>1640.0</cy>
			<w>66.99999237060547</w>
			<h>167.0</h>
			<angle>1.1851624771690343</angle>
		</robndbox>
		<extra/>
	</object>
   <object>
		<name>small-vehicle</name>
		<pose>Unspecified</pose>
		<truncated>0</truncated>
		<difficult>0</difficult>
		<robndbox>
			<cx>174.0</cx>
			<cy>1843.0</cy>
			<w>65.00010681152344</w>
			<h>144.0</h>
			<angle>1.3553149855069935</angle>
		</robndbox>
		<extra/>
	</object>
   <object>
		<name>two-wheeler</name>
		<pose>Unspecified</pose>
		<truncated>0</truncated>
		<difficult>0</difficult>
		<robndbox>
			<cx>3353.0</cx>
			<cy>1531.0</cy>
			<w>25.000022888183594</w>
			<h>70.0001449584961</h>
			<angle>-1.487655682580607</angle>
		</robndbox>
		<extra/>
	</object>
  </annotation>
