   <annotation>
	<folder>train</folder>
	<filename>DJI_20191231173735_0003_frame_4400.png</filename>
	<path>C:\Users\realt\AI\DroneTruth\train\DJI_20191231173735_0003_frame_4400.png</path>
	<source>
		<database>DroneTruth</database>
	</source>
	<size>
		<width>3840</width>
		<height>2160</height>
		<depth>3</depth>
	</size>
	<segmented>0</segmented>
       <object>
		<name>small-vehicle</name>
		<pose>Unspecified</pose>
		<truncated>0</truncated>
		<difficult>0</difficult>
		<robndbox>
			<cx>2560.0</cx>
			<cy>806.0</cy>
			<w>78.99999237060547</w>
			<h>196.00015258789062</h>
			<angle>-0.8225760167006184</angle>
		</robndbox>
		<extra/>
	</object>
   <object>
		<name>small-vehicle</name>
		<pose>Unspecified</pose>
		<truncated>0</truncated>
		<difficult>0</difficult>
		<robndbox>
			<cx>2718.0</cx>
			<cy>975.0</cy>
			<w>73.00000762939453</w>
			<h>167.00010681152344</h>
			<angle>-0.7923576330455339</angle>
		</robndbox>
		<extra/>
	</object>
   <object>
		<name>small-vehicle</name>
		<pose>Unspecified</pose>
		<truncated>0</truncated>
		<difficult>0</difficult>
		<robndbox>
			<cx>2854.0</cx>
			<cy>1116.0</cy>
			<w>73.00001525878906</w>
			<h>206.00003051757812</h>
			<angle>-0.8470218318834603</angle>
		</robndbox>
		<extra/>
	</object>
   <object>
		<name>small-vehicle</name>
		<pose>Unspecified</pose>
		<truncated>0</truncated>
		<difficult>0</difficult>
		<robndbox>
			<cx>2998.0</cx>
			<cy>1251.0</cy>
			<w>76.00015258789062</w>
			<h>187.00009155273438</h>
			<angle>-0.7633322286636063</angle>
		</robndbox>
		<extra/>
	</object>
   <object>
		<name>small-vehicle</name>
		<pose>Unspecified</pose>
		<truncated>0</truncated>
		<difficult>0</difficult>
		<robndbox>
			<cx>2495.0</cx>
			<cy>1164.0</cy>
			<w>64.0000228881836</w>
			<h>148.00001525878906</h>
			<angle>-0.9517063986948446</angle>
		</robndbox>
		<extra/>
	</object>
   <object>
		<name>small-vehicle</name>
		<pose>Unspecified</pose>
		<truncated>0</truncated>
		<difficult>0</difficult>
		<robndbox>
			<cx>2686.0</cx>
			<cy>1949.0</cy>
			<w>67.00004577636719</w>
			<h>163.9998779296875</h>
			<angle>1.798378613366276</angle>
		</robndbox>
		<extra/>
	</object>
   <object>
		<name>small-vehicle</name>
		<pose>Unspecified</pose>
		<truncated>0</truncated>
		<difficult>0</difficult>
		<robndbox>
			<cx>1594.0</cx>
			<cy>1618.0</cy>
			<w>67.99995422363281</w>
			<h>174.00010681152344</h>
			<angle>1.5533429245401864</angle>
		</robndbox>
		<extra/>
	</object>
   <object>
		<name>small-vehicle</name>
		<pose>Unspecified</pose>
		<truncated>0</truncated>
		<difficult>0</difficult>
		<robndbox>
			<cx>990.0</cx>
			<cy>1735.0</cy>
			<w>75.00006103515625</w>
			<h>207.0</h>
			<angle>1.2456525348945018</angle>
		</robndbox>
		<extra/>
	</object>
   <object>
		<name>small-vehicle</name>
		<pose>Unspecified</pose>
		<truncated>0</truncated>
		<difficult>0</difficult>
		<robndbox>
			<cx>100.0</cx>
			<cy>1827.0</cy>
			<w>56.99994659423828</w>
			<h>123.00003051757812</h>
			<angle>-1.7557071920408969</angle>
		</robndbox>
		<extra/>
	</object>
   <object>
		<name>small-vehicle</name>
		<pose>Unspecified</pose>
		<truncated>0</truncated>
		<difficult>0</difficult>
		<robndbox>
			<cx>1772.0</cx>
			<cy>359.0</cy>
			<w>69.99996948242188</w>
			<h>178.0</h>
			<angle>-3.0401181591131667</angle>
		</robndbox>
		<extra/>
	</object>
  </annotation>
