<annotation>
	<folder>train</folder>
	<filename>DJI_20191231173735_0002_frame_2400.png</filename>
	<path>C:\Users\realt\AI\DroneTruth\train\DJI_20191231173735_0002_frame_2400.png</path>
	<source>
		<database>Unknown</database>
	</source>
	<size>
		<width>3840</width>
		<height>2160</height>
		<depth>3</depth>
	</size>
	<segmented>0</segmented>
	<object>
		<name>free-zone</name>
		<pose>Unspecified</pose>
		<truncated>0</truncated>
		<difficult>0</difficult>
		<bndbox>
			<xmin>45</xmin>
			<ymin>15</ymin>
			<xmax>1551</xmax>
			<ymax>1327</ymax>
		</bndbox>
		<extra/>
	</object>
	<object>
		<name>free-zone</name>
		<pose>Unspecified</pose>
		<truncated>0</truncated>
		<difficult>0</difficult>
		<bndbox>
			<xmin>1677</xmin>
			<ymin>1076</ymin>
			<xmax>2424</xmax>
			<ymax>1815</ymax>
		</bndbox>
		<extra/>
	</object>
	<object>
		<name>free-zone</name>
		<pose>Unspecified</pose>
		<truncated>1</truncated>
		<difficult>0</difficult>
		<bndbox>
			<xmin>2823</xmin>
			<ymin>1633</ymin>
			<xmax>3835</xmax>
			<ymax>2160</ymax>
		</bndbox>
		<extra/>
	</object>
	<object>
		<name>group-two-wheeler</name>
		<pose>Unspecified</pose>
		<truncated>0</truncated>
		<difficult>0</difficult>
		<bndbox>
			<xmin>2096</xmin>
			<ymin>1845</ymin>
			<xmax>2198</xmax>
			<ymax>1931</ymax>
		</bndbox>
		<extra/>
	</object>
	<object>
		<name>group-two-wheeler</name>
		<pose>Unspecified</pose>
		<truncated>0</truncated>
		<difficult>0</difficult>
		<bndbox>
			<xmin>3266</xmin>
			<ymin>1538</ymin>
			<xmax>3408</xmax>
			<ymax>1647</ymax>
		</bndbox>
		<extra/>
	</object>
	<object>
		<name>small-vehicle</name>
		<pose>Unspecified</pose>
		<truncated>0</truncated>
		<difficult>0</difficult>
		<robndbox>
			<cx>1202.0</cx>
			<cy>1455.0</cy>
			<w>63.9999</w>
			<h>169.0001</h>
			<angle>4.064275</angle>
		</robndbox>
		<extra/>
	</object>
	<object>
		<name>small-vehicle</name>
		<pose>Unspecified</pose>
		<truncated>0</truncated>
		<difficult>0</difficult>
		<robndbox>
			<cx>2539.0</cx>
			<cy>807.0</cy>
			<w>73.9999</w>
			<h>196.0001</h>
			<angle>5.445427</angle>
		</robndbox>
		<extra/>
	</object>
	<object>
		<name>small-vehicle</name>
		<pose>Unspecified</pose>
		<truncated>0</truncated>
		<difficult>0</difficult>
		<robndbox>
			<cx>2697.0</cx>
			<cy>978.0</cy>
			<w>67.9999</w>
			<h>166.0001</h>
			<angle>5.508281</angle>
		</robndbox>
		<extra/>
	</object>
	<object>
		<name>small-vehicle</name>
		<pose>Unspecified</pose>
		<truncated>0</truncated>
		<difficult>0</difficult>
		<robndbox>
			<cx>2835.0</cx>
			<cy>1120.0</cy>
			<w>71.0</w>
			<h>205.0002</h>
			<angle>5.438632</angle>
		</robndbox>
		<extra/>
	</object>
	<object>
		<name>small-vehicle</name>
		<pose>Unspecified</pose>
		<truncated>0</truncated>
		<difficult>0</difficult>
		<robndbox>
			<cx>2979.0</cx>
			<cy>1257.0</cy>
			<w>73.0002</w>
			<h>183.0001</h>
			<angle>5.510475</angle>
		</robndbox>
		<extra/>
	</object>
	<object>
		<name>small-vehicle</name>
		<pose>Unspecified</pose>
		<truncated>0</truncated>
		<difficult>0</difficult>
		<robndbox>
			<cx>2668.0</cx>
			<cy>1952.0</cy>
			<w>66.0</w>
			<h>160.9999</h>
			<angle>1.783629</angle>
		</robndbox>
		<extra/>
	</object>
	<object>
		<name>small-vehicle</name>
		<pose>Unspecified</pose>
		<truncated>0</truncated>
		<difficult>0</difficult>
		<robndbox>
			<cx>595.0</cx>
			<cy>1742.0</cy>
			<w>64.0</w>
			<h>175.0</h>
			<angle>4.384022</angle>
		</robndbox>
		<extra/>
	</object>
	<object>
		<name>small-vehicle</name>
		<pose>Unspecified</pose>
		<truncated>0</truncated>
		<difficult>0</difficult>
		<robndbox>
			<cx>2791.0</cx>
			<cy>1396.0</cy>
			<w>64.0001</w>
			<h>149.0</h>
			<angle>5.118029</angle>
		</robndbox>
		<extra/>
	</object>
	<object>
		<name>small-vehicle</name>
		<pose>Unspecified</pose>
		<truncated>0</truncated>
		<difficult>0</difficult>
		<robndbox>
			<cx>2547.0</cx>
			<cy>1258.0</cy>
			<w>69.0</w>
			<h>171.9999</h>
			<angle>5.328686</angle>
		</robndbox>
		<extra/>
	</object>
	<object>
		<name>small-vehicle</name>
		<pose>Unspecified</pose>
		<truncated>0</truncated>
		<difficult>0</difficult>
		<robndbox>
			<cx>2294.0</cx>
			<cy>978.0</cy>
			<w>67.9999</w>
			<h>169.0</h>
			<angle>6.007908</angle>
		</robndbox>
		<extra/>
	</object>
	<object>
		<name>large-vehicle</name>
		<pose>Unspecified</pose>
		<truncated>0</truncated>
		<difficult>0</difficult>
		<robndbox>
			<cx>1615.0</cx>
			<cy>1004.0</cy>
			<w>78.0001</w>
			<h>224.0001</h>
			<angle>3.403098</angle>
		</robndbox>
		<extra/>
	</object>
	<object>
		<name>two-wheeler</name>
		<pose>Unspecified</pose>
		<truncated>0</truncated>
		<difficult>0</difficult>
		<robndbox>
			<cx>3331.4407</cx>
			<cy>1586.0879</cy>
			<w>31.8808</w>
			<h>99.1817</h>
			<angle>4.772938</angle>
		</robndbox>
		<extra/>
	</object>
	<object>
		<name>two-wheeler</name>
		<pose>Unspecified</pose>
		<truncated>0</truncated>
		<difficult>0</difficult>
		<robndbox>
			<cx>2145.9429</cx>
			<cy>1880.0377</cy>
			<w>25.2933</w>
			<h>65.4214</h>
			<angle>1.22932</angle>
		</robndbox>
		<extra/>
	</object>
	<object>
		<name>small-vehicle</name>
		<pose>Unspecified</pose>
		<truncated>0</truncated>
		<difficult>0</difficult>
		<robndbox>
			<cx>1686.0</cx>
			<cy>602.0</cy>
			<w>67.0</w>
			<h>169.0</h>
			<angle>3.331019</angle>
		</robndbox>
		<extra/>
	</object>
	<object>
		<name>small-vehicle</name>
		<pose>Unspecified</pose>
		<truncated>0</truncated>
		<difficult>0</difficult>
		<robndbox>
			<cx>1798.0</cx>
			<cy>216.0</cy>
			<w>67.0</w>
			<h>178.0</h>
			<angle>3.201321</angle>
		</robndbox>
		<extra/>
	</object>
</annotation>
