<annotation>
	<folder>train</folder>
	<filename>DJI_20220405115514_0009_frame_1800.png</filename>
	<path>C:\Users\realt\AI\DroneTruth\train\DJI_20220405115514_0009_frame_1800.png</path>
	<source>
		<database>Unknown</database>
	</source>
	<size>
		<width>3840</width>
		<height>2160</height>
		<depth>3</depth>
	</size>
	<segmented>0</segmented>
	<object>
		<name>small-vehicle</name>
		<pose>Unspecified</pose>
		<truncated>0</truncated>
		<difficult>0</difficult>
		<robndbox>
			<cx>225.0</cx>
			<cy>1213.0</cy>
			<w>63.9999</w>
			<h>140.0</h>
			<angle>4.496799</angle>
		</robndbox>
		<extra/>
	</object>
	<object>
		<name>small-vehicle</name>
		<pose>Unspecified</pose>
		<truncated>0</truncated>
		<difficult>0</difficult>
		<robndbox>
			<cx>267.0</cx>
			<cy>1360.0</cy>
			<w>67.0</w>
			<h>166.0</h>
			<angle>4.572762</angle>
		</robndbox>
		<extra/>
	</object>
	<object>
		<name>large-vehicle</name>
		<pose>Unspecified</pose>
		<truncated>0</truncated>
		<difficult>0</difficult>
		<robndbox>
			<cx>495.0</cx>
			<cy>1193.0</cy>
			<w>84.0</w>
			<h>192.0</h>
			<angle>3.826352</angle>
		</robndbox>
		<extra/>
	</object>
	<object>
		<name>two-wheeler</name>
		<pose>Unspecified</pose>
		<truncated>0</truncated>
		<difficult>0</difficult>
		<robndbox>
			<cx>1173.0</cx>
			<cy>1152.0</cy>
			<w>33.0</w>
			<h>61.0</h>
			<angle>4.712389</angle>
		</robndbox>
		<extra/>
	</object>
	<object>
		<name>small-vehicle</name>
		<pose>Unspecified</pose>
		<truncated>0</truncated>
		<difficult>0</difficult>
		<robndbox>
			<cx>1280.0</cx>
			<cy>1284.0</cy>
			<w>68.0</w>
			<h>175.0001</h>
			<angle>4.712612</angle>
		</robndbox>
		<extra/>
	</object>
	<object>
		<name>large-vehicle</name>
		<pose>Unspecified</pose>
		<truncated>0</truncated>
		<difficult>0</difficult>
		<robndbox>
			<cx>1293.0</cx>
			<cy>1387.0</cy>
			<w>69.0</w>
			<h>196.0</h>
			<angle>4.712389</angle>
		</robndbox>
		<extra/>
	</object>
	<object>
		<name>small-vehicle</name>
		<pose>Unspecified</pose>
		<truncated>0</truncated>
		<difficult>0</difficult>
		<robndbox>
			<cx>1343.0</cx>
			<cy>1179.0</cy>
			<w>72.0</w>
			<h>180.0001</h>
			<angle>4.71403</angle>
		</robndbox>
		<extra/>
	</object>
	<object>
		<name>small-vehicle</name>
		<pose>Unspecified</pose>
		<truncated>0</truncated>
		<difficult>0</difficult>
		<robndbox>
			<cx>1528.0</cx>
			<cy>1282.0</cy>
			<w>69.0001</w>
			<h>181.0001</h>
			<angle>4.709988</angle>
		</robndbox>
		<extra/>
	</object>
	<object>
		<name>small-vehicle</name>
		<pose>Unspecified</pose>
		<truncated>0</truncated>
		<difficult>0</difficult>
		<robndbox>
			<cx>1542.0</cx>
			<cy>1387.0</cy>
			<w>65.0</w>
			<h>163.9999</h>
			<angle>4.718775</angle>
		</robndbox>
		<extra/>
	</object>
	<object>
		<name>large-vehicle</name>
		<pose>Unspecified</pose>
		<truncated>0</truncated>
		<difficult>0</difficult>
		<robndbox>
			<cx>1761.0</cx>
			<cy>1392.0</cy>
			<w>62.0</w>
			<h>179.0</h>
			<angle>4.732981</angle>
		</robndbox>
		<extra/>
	</object>
	<object>
		<name>large-vehicle</name>
		<pose>Unspecified</pose>
		<truncated>0</truncated>
		<difficult>0</difficult>
		<robndbox>
			<cx>2016.0</cx>
			<cy>1396.0</cy>
			<w>78.0</w>
			<h>198.0001</h>
			<angle>4.724353</angle>
		</robndbox>
		<extra/>
	</object>
	<object>
		<name>small-vehicle</name>
		<pose>Unspecified</pose>
		<truncated>0</truncated>
		<difficult>0</difficult>
		<robndbox>
			<cx>2282.0</cx>
			<cy>1390.0</cy>
			<w>68.0</w>
			<h>176.0002</h>
			<angle>4.72136</angle>
		</robndbox>
		<extra/>
	</object>
	<object>
		<name>small-vehicle</name>
		<pose>Unspecified</pose>
		<truncated>0</truncated>
		<difficult>0</difficult>
		<robndbox>
			<cx>2699.0</cx>
			<cy>1392.0</cy>
			<w>70.0</w>
			<h>177.9999</h>
			<angle>4.711266</angle>
		</robndbox>
		<extra/>
	</object>
	<object>
		<name>small-vehicle</name>
		<pose>Unspecified</pose>
		<truncated>0</truncated>
		<difficult>0</difficult>
		<robndbox>
			<cx>3071.0</cx>
			<cy>1397.0</cy>
			<w>68.0</w>
			<h>174.0001</h>
			<angle>4.729842</angle>
		</robndbox>
		<extra/>
	</object>
	<object>
		<name>small-vehicle</name>
		<pose>Unspecified</pose>
		<truncated>0</truncated>
		<difficult>0</difficult>
		<robndbox>
			<cx>3480.0</cx>
			<cy>1372.0</cy>
			<w>66.9999</w>
			<h>174.0</h>
			<angle>4.626884</angle>
		</robndbox>
		<extra/>
	</object>
	<object>
		<name>large-vehicle</name>
		<pose>Unspecified</pose>
		<truncated>0</truncated>
		<difficult>0</difficult>
		<robndbox>
			<cx>3564.0718</cx>
			<cy>1174.349</cy>
			<w>96.7033</w>
			<h>481.9336</h>
			<angle>4.723185</angle>
		</robndbox>
		<extra/>
	</object>
</annotation>
